{"stat.flyOneCm":717352,"stat.useItem.minecraft.glass":1,"stat.walkOneCm":186645,"stat.jump":278,"stat.useItem.minecraft.quartz_block":805,"stat.playOneMinute":72637,"stat.fallOneCm":422,"achievement.openInventory":83,"stat.useItem.minecraft.planks":70,"stat.useItem.minecraft.stone":61,"stat.leaveGame":1,"stat.useItem.minecraft.iron_block":102,"stat.crouchOneCm":15141,"stat.useItem.minecraft.coal_block":12,"stat.useItem.minecraft.wool":120,"stat.timeSinceDeath":72637,"stat.useItem.minecraft.gold_block":184,"stat.useItem.minecraft.emerald_block":7,"stat.sprintOneCm":67920,"stat.useItem.minecraft.stained_glass":38,"achievement.exploreAllBiomes":{"value":0,"progress":["Plains"]}}